geocircle/__init__.py
geocircle/cli.py
geocircle/geocircle.py
geocircle-0.2.0.dist-info/AUTHORS.rst
geocircle-0.2.0.dist-info/LICENSE
geocircle-0.2.0.dist-info/METADATA
geocircle-0.2.0.dist-info/WHEEL
geocircle-0.2.0.dist-info/entry_points.txt
geocircle-0.2.0.dist-info/top_level.txt
geocircle-0.2.0.dist-info/RECORD
